Workbook

Sheet Start Here
A1: REAL ESTATE AGENT PLANNER
A2: South African Estate Agent · Daily Business & Property Planner
A4: AGENT DETAILS | D4: DAILY WORKING ROUTINE
A5: Agent name | B5: Luzaan | D5: 08:00 | E5: Plan and prepare – review the daily schedule, outstanding tasks and address route.
A6: Agency name | D6: 09:00 | E6: Find potential sellers – make calls, respond to enquiries, identify listing opportunities.
A7: Contact number | D7: 11:00 | E7: Work the area – visit planned addresses and attend appointments.
A8: Email address | D8: 13:00 | E8: Buyers and properties – manage property information, buyer requirements and viewings.
A9: Primary farming area | D9: 15:00 | E9: Follow-ups and review – update records, contact clients, confirm tomorrow's appointments, review the day.
A10: Month and year | B10: Mossel Bay & surrounds (edit) | D10: Times are examples; adjust to suit your agency.
A12: DAILY BUSINESS PRIORITIES | D12: TABS
A13: 1. Find potential properties. | D13: Daily Planner – day-by-day goals, checklist, results
A14: 2. Connect with potential sellers and landlords. | D14: Route Planner – addresses and visit order
A15: 3. Build relationships with buyers. | D15: Seller Leads – your most important tab
A16: 4. Complete follow-ups. | D16: Calls & Follow-ups – conversation log
A17: 5. Grow your property portfolio. | D17: Buyers – requirement profiles
D18: Viewings – one row per viewing
A19: HOW TO USE THIS PLANNER | D19: Properties – information sheet and marketing checks
A20: 1. Plan: fill in the Daily Planner the evening before (type the first date; the rest follow). | D20: Weekly Tracker – targets and review
A21: 2. Route: list tomorrow's visits on Route Planner, grouped by area. | D21: Area & Marketing – farming knowledge and plan
A22: 3. Log: capture every seller, landlord and buyer conversation straight away. | D22: Compliance – checklist and transaction tracker
A23: 4. Follow up: Seller Leads and Calls tabs flag OVERDUE / TODAY automatically. | D23: Monthly Review – totals and reflection
A24: 5. Review: update Weekly Tracker every Friday and Monthly Review at month end.
A25: 6. Tick boxes: pick ✓ from the dropdown in any tick column.
A27: Important: the compliance section is an organisational aid, not legal advice. Confirm current South African requirements and your agency's procedures with your principal or compliance officer.

Sheet Daily Planner
A1: DAILY PLANNER & ACTION CHECKLIST
A2: Type the first date in B3 – following working days fill in. Overwrite any date if you work Saturdays.
A3: Start date:
A5: Date | B5: Day | C5: Main goal for the day | D5: Contact potential sellers | E5: Search new property leads | F5: Calls & enquiries | G5: Follow up clients | H5: Plan property visits | I5: Update agency records | J5: Ask for referrals | K5: Confirm tomorrow's appts | L5: Review daily performance | M5: Planned appointments & times | N5: Addresses to visit / contacts | O5: Results and next steps | P5: Checklist %
A6: =$B$3 | B6: =IF(A6="","",TEXT(A6,"dddd")) | P6: =IF(A6="","",COUNTIF(D6:L6,"✓")/9)
A7: =IF(A6="","",WORKDAY(A6,1)) | B7: =IF(A7="","",TEXT(A7,"dddd")) | P7: =IF(A7="","",COUNTIF(D7:L7,"✓")/9)
A8: =IF(A7="","",WORKDAY(A7,1)) | B8: =IF(A8="","",TEXT(A8,"dddd")) | P8: =IF(A8="","",COUNTIF(D8:L8,"✓")/9)
A9: =IF(A8="","",WORKDAY(A8,1)) | B9: =IF(A9="","",TEXT(A9,"dddd")) | P9: =IF(A9="","",COUNTIF(D9:L9,"✓")/9)
A10: =IF(A9="","",WORKDAY(A9,1)) | B10: =IF(A10="","",TEXT(A10,"dddd")) | P10: =IF(A10="","",COUNTIF(D10:L10,"✓")/9)
A11: =IF(A10="","",WORKDAY(A10,1)) | B11: =IF(A11="","",TEXT(A11,"dddd")) | P11: =IF(A11="","",COUNTIF(D11:L11,"✓")/9)
A12: =IF(A11="","",WORKDAY(A11,1)) | B12: =IF(A12="","",TEXT(A12,"dddd")) | P12: =IF(A12="","",COUNTIF(D12:L12,"✓")/9)
A13: =IF(A12="","",WORKDAY(A12,1)) | B13: =IF(A13="","",TEXT(A13,"dddd")) | P13: =IF(A13="","",COUNTIF(D13:L13,"✓")/9)
A14: =IF(A13="","",WORKDAY(A13,1)) | B14: =IF(A14="","",TEXT(A14,"dddd")) | P14: =IF(A14="","",COUNTIF(D14:L14,"✓")/9)
A15: =IF(A14="","",WORKDAY(A14,1)) | B15: =IF(A15="","",TEXT(A15,"dddd")) | P15: =IF(A15="","",COUNTIF(D15:L15,"✓")/9)
A16: =IF(A15="","",WORKDAY(A15,1)) | B16: =IF(A16="","",TEXT(A16,"dddd")) | P16: =IF(A16="","",COUNTIF(D16:L16,"✓")/9)
A17: =IF(A16="","",WORKDAY(A16,1)) | B17: =IF(A17="","",TEXT(A17,"dddd")) | P17: =IF(A17="","",COUNTIF(D17:L17,"✓")/9)
A18: =IF(A17="","",WORKDAY(A17,1)) | B18: =IF(A18="","",TEXT(A18,"dddd")) | P18: =IF(A18="","",COUNTIF(D18:L18,"✓")/9)
... A45: =IF(A44="","",WORKDAY(A44,1)) | B45: =IF(A45="","",TEXT(A45,"dddd")) | P45: =IF(A45="","",COUNTIF(D45:L45,"✓")/9)

Sheet Route Planner
A1: ADDRESS & ROUTE PLANNER
A2: Reduce unnecessary driving, save fuel and maximise productive visits. Sort by Date then Order.
A4: Date | B4: Farming area | C4: Starting / finishing point | D4: Order | E4: Street address / complex | F4: Reason for visit | G4: Lead source | H4: Planned time | I4: Access notes (authorised only) | J4: Result and next steps | K4: Revisit?

Sheet Seller Leads
A1: SELLER & LANDLORD LEAD TRACKER
A2: Finding properties to sell or rent. Follow-up flag turns red when overdue.
A4: Date identified | B4: Seller / landlord name | C4: Property address | D4: Phone | E4: Email | F4: Preferred contact | G4: Reason for selling / renting | H4: Expected timeframe | I4: Status | J4: Next action | K4: Follow-up date | L4: Flag | M4: Notes | O4: SELLER CONVERSATION PROMPTS
L5: =IF(OR(K5="",I5="Closed",I5="Active listing"),"",IF(K5<TODAY(),"OVERDUE",IF(K5=TODAY(),"TODAY",""))) | O5: 1. Are you considering selling or renting your property?
L6: =IF(OR(K6="",I6="Closed",I6="Active listing"),"",IF(K6<TODAY(),"OVERDUE",IF(K6=TODAY(),"TODAY",""))) | O6: 2. What timeframe would suit you?
L7: =IF(OR(K7="",I7="Closed",I7="Active listing"),"",IF(K7<TODAY(),"OVERDUE",IF(K7=TODAY(),"TODAY",""))) | O7: 3. Would you like a market-related property discussion?
L8: =IF(OR(K8="",I8="Closed",I8="Active listing"),"",IF(K8<TODAY(),"OVERDUE",IF(K8=TODAY(),"TODAY",""))) | O8: 4. What are you looking for in an estate agent?
L9: =IF(OR(K9="",I9="Closed",I9="Active listing"),"",IF(K9<TODAY(),"OVERDUE",IF(K9=TODAY(),"TODAY",""))) | O9: 5. May I contact you again, and when would suit you?
L10: =IF(OR(K10="",I10="Closed",I10="Active listing"),"",IF(K10<TODAY(),"OVERDUE",IF(K10=TODAY(),"TODAY","")))
L11: =IF(OR(K11="",I11="Closed",I11="Active listing"),"",IF(K11<TODAY(),"OVERDUE",IF(K11=TODAY(),"TODAY","")))
L12: =IF(OR(K12="",I12="Closed",I12="Active listing"),"",IF(K12<TODAY(),"OVERDUE",IF(K12=TODAY(),"TODAY","")))
L13: =IF(OR(K13="",I13="Closed",I13="Active listing"),"",IF(K13<TODAY(),"OVERDUE",IF(K13=TODAY(),"TODAY","")))
L14: =IF(OR(K14="",I14="Closed",I14="Active listing"),"",IF(K14<TODAY(),"OVERDUE",IF(K14=TODAY(),"TODAY","")))
L15: =IF(OR(K15="",I15="Closed",I15="Active listing"),"",IF(K15<TODAY(),"OVERDUE",IF(K15=TODAY(),"TODAY","")))
L16: =IF(OR(K16="",I16="Closed",I16="Active listing"),"",IF(K16<TODAY(),"OVERDUE",IF(K16=TODAY(),"TODAY","")))
L17: =IF(OR(K17="",I17="Closed",I17="Active listing"),"",IF(K17<TODAY(),"OVERDUE",IF(K17=TODAY(),"TODAY","")))
L18: =IF(OR(K18="",I18="Closed",I18="Active listing"),"",IF(K18<TODAY(),"OVERDUE",IF(K18=TODAY(),"TODAY","")))
L19: =IF(OR(K19="",I19="Closed",I19="Active listing"),"",IF(K19<TODAY(),"OVERDUE",IF(K19=TODAY(),"TODAY","")))
L20: =IF(OR(K20="",I20="Closed",I20="Active listing"),"",IF(K20<TODAY(),"OVERDUE",IF(K20=TODAY(),"TODAY","")))
L21: =IF(OR(K21="",I21="Closed",I21="Active listing"),"",IF(K21<TODAY(),"OVERDUE",IF(K21=TODAY(),"TODAY","")))
... L200: =IF(OR(K200="",I200="Closed",I200="Active listing"),"",IF(K200<TODAY(),"OVERDUE",IF(K200=TODAY(),"TODAY","")))

Sheet Calls & Follow-ups
A1: CALLS, MESSAGES & FOLLOW-UP LOG
A2: So no enquiry or opportunity is forgotten.
A4: Date & time | B4: Person contacted | C4: Method | D4: Conversation summary | E4: Information promised | F4: Next action | G4: Follow-up deadline | H4: Status | I4: Flag
I5: =IF(OR(G5="",H5="Done"),"",IF(G5<TODAY(),"OVERDUE",IF(G5=TODAY(),"TODAY","")))
I6: =IF(OR(G6="",H6="Done"),"",IF(G6<TODAY(),"OVERDUE",IF(G6=TODAY(),"TODAY","")))
I7: =IF(OR(G7="",H7="Done"),"",IF(G7<TODAY(),"OVERDUE",IF(G7=TODAY(),"TODAY","")))
I8: =IF(OR(G8="",H8="Done"),"",IF(G8<TODAY(),"OVERDUE",IF(G8=TODAY(),"TODAY","")))
I9: =IF(OR(G9="",H9="Done"),"",IF(G9<TODAY(),"OVERDUE",IF(G9=TODAY(),"TODAY","")))
I10: =IF(OR(G10="",H10="Done"),"",IF(G10<TODAY(),"OVERDUE",IF(G10=TODAY(),"TODAY","")))
I11: =IF(OR(G11="",H11="Done"),"",IF(G11<TODAY(),"OVERDUE",IF(G11=TODAY(),"TODAY","")))
I12: =IF(OR(G12="",H12="Done"),"",IF(G12<TODAY(),"OVERDUE",IF(G12=TODAY(),"TODAY","")))
I13: =IF(OR(G13="",H13="Done"),"",IF(G13<TODAY(),"OVERDUE",IF(G13=TODAY(),"TODAY","")))
I14: =IF(OR(G14="",H14="Done"),"",IF(G14<TODAY(),"OVERDUE",IF(G14=TODAY(),"TODAY","")))
I15: =IF(OR(G15="",H15="Done"),"",IF(G15<TODAY(),"OVERDUE",IF(G15=TODAY(),"TODAY","")))
I16: =IF(OR(G16="",H16="Done"),"",IF(G16<TODAY(),"OVERDUE",IF(G16=TODAY(),"TODAY","")))
... I200: =IF(OR(G200="",H200="Done"),"",IF(G200<TODAY(),"OVERDUE",IF(G200=TODAY(),"TODAY","")))

Sheet Buyers
A1: BUYER REQUIREMENTS PROFILES
A2: One row per buyer.
A4: Buyer name | B4: Contact details | C4: Preferred suburbs / areas | D4: Budget min (R) | E4: Budget max (R) | F4: Financing / pre-approval | G4: Property type | H4: Bedrooms | I4: Bathrooms | J4: Parking | K4: Garden / pets | L4: Must-have features | M4: Deal-breakers | N4: Ideal moving date | O4: Decision-makers | P4: Properties sent | Q4: Viewing feedback | R4: Next step

Sheet Viewings
A1: PROPERTY VIEWING RECORD
A2: One row per viewing. Tick the checklist columns before and after each viewing.
A4: Date & time | B4: Property address | C4: Listing ref | D4: Buyer name | E4: Features discussed | F4: Positive feedback | G4: Concerns / questions | H4: Interest level | I4: Offer discussion | J4: Agreed next action | K4: Follow-up date | L4: Arrangements confirmed | M4: Property info reviewed | N4: Authorised access confirmed | O4: Respected property & occupants | P4: Feedback recorded | Q4: Secured & keys returned | R4: Next follow-up scheduled

Sheet Properties
A1: PROPERTY INFORMATION SHEET
A2: One row per property marketed or considered. Only record verified information.
A4: Address | B4: Listing ID | C4: Property type | D4: Asking price (R) | E4: Beds | F4: Baths | G4: Garage / parking | H4: Land size (m²) | I4: Floor area (m², verified) | J4: Rates (R/m) | K4: Levies (R/m) | L4: Utilities | M4: Main selling points | N4: Disclosures / open questions | O4: Viewing arrangements | P4: Documents still required | Q4: Owner / authorised contact | R4: Last contact date | S4: Authority to market confirmed | T4: Info verified | U4: Listing status & price confirmed | V4: Photo/video permission | W4: Ads checked for accuracy | X4: Approved branding used | Y4: Enquiries recorded

Sheet Weekly Tracker
A1: WEEKLY TARGETS & PERFORMANCE TRACKER
A2: Set targets in row 5. Totals (row 6) add up all weeks. Row 7 shows last week's result vs target.
A4: Week starting | B4: New seller leads | C4: Seller conversations | D4: Seller appointments | E4: Follow-ups completed | F4: Buyer consultations | G4: Property viewings | H4: Referrals requested | I4: Listing presentations | J4: Mandates won | K4: Best result | L4: Where leads came from | M4: What worked well | N4: What needs improvement | O4: Three priorities for next week
A5: Weekly target
A6: Total to date | B6: =SUM(B9:B60) | C6: =SUM(C9:C60) | D6: =SUM(D9:D60) | E6: =SUM(E9:E60) | F6: =SUM(F9:F60) | G6: =SUM(G9:G60) | H6: =SUM(H9:H60) | I6: =SUM(I9:I60) | J6: =SUM(J9:J60)
A8: Weeks

Sheet Area & Marketing
A1: AREA KNOWLEDGE & MARKETING PLAN
A2: Build local knowledge of your farming area. Record only verified sales and approved marketing.
A3: AREA KNOWLEDGE
A4: Suburb / neighbourhood | B4: Common property types | C4: Market information to research | D4: Verified comparable sales (address · price · date · source) | E4: Local amenities & attractions | F4: Transport links & facilities | G4: Date reviewed
A27: MARKETING PLAN
A28: Marketing idea | B28: Target audience | C28: Planned date | D28: Approvals & permissions | E28: Results | F28: Notes

Sheet Compliance
A1: SOUTH AFRICAN COMPLIANCE & TRANSACTION TRACKER
A2: Organisational aid only – not legal advice. Confirm requirements with your principal or compliance officer.
A3: COMPLIANCE REMINDER CHECKLIST (use per property: copy the tick column or log in Notes)
A4: Reminder | B4: Done ✓ | C4: Date checked | D4: Property / client | E4: Notes
A5: Confirm authority to market the property
A6: Verify owner or authorised representative details
A7: Confirm listing status and approved asking price
A8: Check required disclosures and records
A9: Ensure advertising is accurate and not misleading
A10: Obtain necessary permissions for access and photographs
A11: Follow applicable FICA and verification procedures
A12: Protect personal and client information
A13: Record instructions and important communications
A14: Refer compliance questions to the principal or compliance officer
A17: TRANSACTION PROGRESS TRACKER
A18: Property / client | B18: Outstanding task | C18: Responsible person | D18: Due date | E18: Status

Sheet Monthly Review
A1: MONTHLY PERFORMANCE REVIEW
A2: Blue-grey rows are calculated from your other tabs; the rest you enter. Type the first day of each month in row 4.
A4: Month (first day) | B4: =DATE(YEAR(TODAY()),1,1) | C4: =EDATE(B4,1) | D4: =EDATE(C4,1) | E4: =EDATE(D4,1) | F4: =EDATE(E4,1) | G4: =EDATE(F4,1) | H4: =EDATE(G4,1) | I4: =EDATE(H4,1) | J4: =EDATE(I4,1) | ... M4: =EDATE(L4,1)
A5: New seller leads (auto) | B5: =COUNTIFS('Seller Leads'!$A$5:$A$200,">="&B$4,'Seller Leads'!$A$5:$A$200,"<"&EDATE(B$4,1)) | C5: =COUNTIFS('Seller Leads'!$A$5:$A$200,">="&C$4,'Seller Leads'!$A$5:$A$200,"<"&EDATE(C$4,1)) | D5: =COUNTIFS('Seller Leads'!$A$5:$A$200,">="&D$4,'Seller Leads'!$A$5:$A$200,"<"&EDATE(D$4,1)) | E5: =COUNTIFS('Seller Leads'!$A$5:$A$200,">="&E$4,'Seller Leads'!$A$5:$A$200,"<"&EDATE(E$4,1)) | F5: =COUNTIFS('Seller Leads'!$A$5:$A$200,">="&F$4,'Seller Leads'!$A$5:$A$200,"<"&EDATE(F$4,1)) | G5: =COUNTIFS('Seller Leads'!$A$5:$A$200,">="&G$4,'Seller Leads'!$A$5:$A$200,"<"&EDATE(G$4,1)) | H5: =COUNTIFS('Seller Leads'!$A$5:$A$200,">="&H$4,'Seller Leads'!$A$5:$A$200,"<"&EDATE(H$4,1)) | I5: =COUNTIFS('Seller Leads'!$A$5:$A$200,">="&I$4,'Seller Leads'!$A$5:$A$200,"<"&EDATE(I$4,1)) | ... M5: =COUNTIFS('Seller Leads'!$A$5:$A$200,">="&M$4,'Seller Leads'!$A$5:$A$200,"<"&EDATE(M$4,1))
A6: Seller appointments
A7: Mandates or listings won
A8: Buyer consultations
A9: Property viewings (auto) | B9: =COUNTIFS(Viewings!$A$5:$A$150,">="&B$4,Viewings!$A$5:$A$150,"<"&EDATE(B$4,1)) | C9: =COUNTIFS(Viewings!$A$5:$A$150,">="&C$4,Viewings!$A$5:$A$150,"<"&EDATE(C$4,1)) | D9: =COUNTIFS(Viewings!$A$5:$A$150,">="&D$4,Viewings!$A$5:$A$150,"<"&EDATE(D$4,1)) | E9: =COUNTIFS(Viewings!$A$5:$A$150,">="&E$4,Viewings!$A$5:$A$150,"<"&EDATE(E$4,1)) | F9: =COUNTIFS(Viewings!$A$5:$A$150,">="&F$4,Viewings!$A$5:$A$150,"<"&EDATE(F$4,1)) | G9: =COUNTIFS(Viewings!$A$5:$A$150,">="&G$4,Viewings!$A$5:$A$150,"<"&EDATE(G$4,1)) | H9: =COUNTIFS(Viewings!$A$5:$A$150,">="&H$4,Viewings!$A$5:$A$150,"<"&EDATE(H$4,1)) | I9: =COUNTIFS(Viewings!$A$5:$A$150,">="&I$4,Viewings!$A$5:$A$150,"<"&EDATE(I$4,1)) | ... M9: =COUNTIFS(Viewings!$A$5:$A$150,">="&M$4,Viewings!$A$5:$A$150,"<"&EDATE(M$4,1))
A10: Offers and transactions progressed
A11: Follow-ups completed (auto) | B11: =COUNTIFS('Calls & Follow-ups'!$G$5:$G$200,">="&B$4,'Calls & Follow-ups'!$G$5:$G$200,"<"&EDATE(B$4,1),'Calls & Follow-ups'!$H$5:$H$200,"Done") | C11: =COUNTIFS('Calls & Follow-ups'!$G$5:$G$200,">="&C$4,'Calls & Follow-ups'!$G$5:$G$200,"<"&EDATE(C$4,1),'Calls & Follow-ups'!$H$5:$H$200,"Done") | D11: =COUNTIFS('Calls & Follow-ups'!$G$5:$G$200,">="&D$4,'Calls & Follow-ups'!$G$5:$G$200,"<"&EDATE(D$4,1),'Calls & Follow-ups'!$H$5:$H$200,"Done") | E11: =COUNTIFS('Calls & Follow-ups'!$G$5:$G$200,">="&E$4,'Calls & Follow-ups'!$G$5:$G$200,"<"&EDATE(E$4,1),'Calls & Follow-ups'!$H$5:$H$200,"Done") | F11: =COUNTIFS('Calls & Follow-ups'!$G$5:$G$200,">="&F$4,'Calls & Follow-ups'!$G$5:$G$200,"<"&EDATE(F$4,1),'Calls & Follow-ups'!$H$5:$H$200,"Done") | G11: =COUNTIFS('Calls & Follow-ups'!$G$5:$G$200,">="&G$4,'Calls & Follow-ups'!$G$5:$G$200,"<"&EDATE(G$4,1),'Calls & Follow-ups'!$H$5:$H$200,"Done") | H11: =COUNTIFS('Calls & Follow-ups'!$G$5:$G$200,">="&H$4,'Calls & Follow-ups'!$G$5:$G$200,"<"&EDATE(H$4,1),'Calls & Follow-ups'!$H$5:$H$200,"Done") | I11: =COUNTIFS('Calls & Follow-ups'!$G$5:$G$200,">="&I$4,'Calls & Follow-ups'!$G$5:$G$200,"<"&EDATE(I$4,1),'Calls & Follow-ups'!$H$5:$H$200,"Done") | ... M11: =COUNTIFS('Calls & Follow-ups'!$G$5:$G$200,">="&M$4,'Calls & Follow-ups'!$G$5:$G$200,"<"&EDATE(M$4,1),'Calls & Follow-ups'!$H$5:$H$200,"Done")
A14: MONTHLY REFLECTION
A15: Month | B15: What will I continue doing? | E15: What will I improve? | H15: Which skill should I develop? | K15: Main business goal next month
A16: =B4
A17: =C4
A18: =D4
A19: =E4
A20: =F4
A21: =G4
A22: =H4
A23: =I4
A24: =J4
A25: =K4
A26: =L4
A27: =M4
